trajectory_manifold/__init__.py
trajectory_manifold/estimation.py
trajectory_manifold/examples.py
trajectory_manifold/helpers.py
trajectory_manifold/manifold.py
trajectory_manifold/optimize.py
trajectory_manifold-0.0.2.dist-info/LICENSE
trajectory_manifold-0.0.2.dist-info/METADATA
trajectory_manifold-0.0.2.dist-info/WHEEL
trajectory_manifold-0.0.2.dist-info/top_level.txt
trajectory_manifold-0.0.2.dist-info/RECORD
